pipeline_views/__init__.py
pipeline_views/exceptions.py
pipeline_views/meta.py
pipeline_views/py.typed
pipeline_views/serializers.py
pipeline_views/typing.py
pipeline_views/utils.py
pipeline_views/views.py
drf_pipeline_views-0.9.2.dist-info/LICENSE
drf_pipeline_views-0.9.2.dist-info/METADATA
drf_pipeline_views-0.9.2.dist-info/WHEEL
drf_pipeline_views-0.9.2.dist-info/RECORD
