Metadata-Version: 2.3
Name: drf-pipeline-views
Version: 0.9.2
Summary: Django REST framework views using the pipeline pattern.
Home-page: https://mrthearman.github.io/drf-pipeline-views
License: MIT
Keywords: django,djangorestframework,drf,pipeline,views
Author: Matti Lamppu
Author-email: lamppu.matti.akseli@gmail.com
Requires-Python: >=3.10,<4
Classifier: Environment :: Web Environment
Classifier: Framework :: Django
Classifier: Programming Language :: Python
Classifier: Programming Language :: Python :: 3
Classifier: Programming Language :: Python :: 3 :: Only
Classifier: Programming Language :: Python :: 3.10
Classifier: Programming Language :: Python :: 3.11
Classifier: Programming Language :: Python :: 3.12
Classifier: Programming Language :: Python :: 3.13
Classifier: Framework :: Django :: 4.2
Classifier: Framework :: Django :: 5.0
Classifier: Framework :: Django :: 5.1
Classifier: Intended Audience :: Developers
Classifier: Natural Language :: English
Requires-Dist: Django (>=4.2)
Requires-Dist: PyYAML (>=6.0)
Requires-Dist: asgiref (>=3.5.0)
Requires-Dist: djangorestframework (>=3.13.0)
Requires-Dist: drf-openapi-schema (>=0.0.3)
Requires-Dist: drf-serializer-inference (>=0.0.2)
Requires-Dist: pydantic (>=1.6.2)
Requires-Dist: uritemplate (>=4.1.1)
Requires-Dist: uvloop (>=0.16.0) ; sys_platform != "win32"
Project-URL: Bug Tracker, https://github.com/MrThearMan/drf-pipeline-views/issues
Project-URL: Documentation, https://mrthearman.github.io/drf-pipeline-views
Project-URL: Repository, https://github.com/MrThearMan/drf-pipeline-views
